windmilltritonv2/__init__.py
windmilltritonv2/client.py
windmilltritonv2/client_factory.py
windmilltritonv2/constants.py
windmilltritonv2/exceptions.py
windmilltritonv2/grpc_aio_client.py
windmilltritonv2/grpc_client.py
windmilltritonv2/http_aio_client.py
windmilltritonv2/http_client.py
windmilltritonv2/utils.py
windmilltritonv2-0.5.0.dist-info/METADATA
windmilltritonv2-0.5.0.dist-info/WHEEL
windmilltritonv2-0.5.0.dist-info/top_level.txt
windmilltritonv2-0.5.0.dist-info/RECORD
