Metadata-Version: 2.1
Name: windmilltritonv2
Version: 0.5.0
Summary: project descriptions here
Home-page: https://console.cloud.baidu-int.com/devops/icode/repos/baidu/themis/windmill-endpoint/tree/master
Author: zhoubohan
Author-email: zhoubohan@baidu.com
License: MIT
Classifier: Programming Language :: Python
Classifier: Programming Language :: Python :: 3
Classifier: Programming Language :: Python :: 3.7
Classifier: Programming Language :: Python :: 3.8
Classifier: Programming Language :: Python :: 3.9
Requires-Python: >=3.7
Requires-Dist: numpy (>=1.23.5)
Requires-Dist: tenacity (>=8.1.0)
Requires-Dist: tritonclient[all] (>=2.25.0)
Requires-Dist: pydantic (>=1.10.2)
